equationtracer/__init__.py
equationtracer/__main__.py
equationtracer/button.py
equationtracer/keyboard.py
equationtracer/main.py
equationtracer/printers.py
equationtracer-1.3.0.dist-info/LICENSE
equationtracer-1.3.0.dist-info/METADATA
equationtracer-1.3.0.dist-info/WHEEL
equationtracer-1.3.0.dist-info/entry_points.txt
equationtracer-1.3.0.dist-info/RECORD
