Metadata-Version: 2.1
Name: equationtracer
Version: 1.3.0
Summary: Uses Discrete Fourier Transform to Turn Scribbles into Equations!
Author: Ying Liqian
Author-email: jamesylq@gmail.com
Requires-Python: >=3.9,<4.0
Classifier: Programming Language :: Python :: 3
Classifier: Programming Language :: Python :: 3.9
Classifier: Programming Language :: Python :: 3.10
Classifier: Programming Language :: Python :: 3.11
Classifier: Programming Language :: Python :: 3.12
Requires-Dist: numpy (>=1.26.3,<2.0.0)
Requires-Dist: pygame (>=2.5.2,<3.0.0)
Requires-Dist: pyperclip (>=1.8.2,<2.0.0)
